[
  {
    "title": "中国国安部促全民树立生物安全意识",
    "link": "/realtime/china/story20231030-1446669",
    "uuid": "69ec3964-6072-4c2f-8c38-353c966659c5",
    "summary": "中国国家安全部发文称，中国的人种基因资源与生物物种资源是境外一些机构、组织和人员的窃密目标，并提醒民众要树立起“生物安全意识”。中国国家安全部微信公众号星期一（10月30日）发布题..."
  },
  {
    "title": "民进党批蓝白不掩饰政治分赃",
    "link": "/realtime/china/story20231030-1446668",
    "uuid": "402b9c43-7bec-4a08-ac56-d3b7c7f451b1",
    "summary": "台湾执政的民进党批评，在野阵营的蓝白政党协商是“毫不掩饰公开上演政治分赃戏码”，并点名指民众党总统参选人柯文哲约会国民党，又幽会鸿海集团创办人郭台铭，“政治操守令人瞠目结舌”。国民..."
  },
  {
    "title": "中国国家能源局：南方部分省份电力保供压力较大",
    "link": "/realtime/china/story20231030-1446651",
    "uuid": "2bbbb40e-1997-4519-94da-7ba16909f64e",
    "summary": "中国国家能源局预告，迎峰度冬期间电力保供总体有保障，但是西北、华东、西南、南方区域的部分省份电力保供压力较大。综合《证券时报》《上海证券报》报道，中国国家能源局新闻发言人张星星期一..."
  },
  {
    "title": "蓝白协商前传会郭台铭 柯文哲：团结一切可团结力量",
    "link": "/realtime/china/story20231030-1446665",
    "uuid": "033cacd7-a744-487f-aead-db7a8c534f1f",
    "summary": "台湾在野阵营的蓝白政党协商登场前一天，民众党总统参选人柯文哲据报与以独立身份参选的鸿海创办人郭台铭密会。柯文哲受访时没有否认，并强调要团结一切可团结的力量。根据《自由时报》，国民党..."
  },
  {
    "title": "香港法院撤销美地方议员无牌持枪控状",
    "link": "/realtime/china/story20231030-1446659",
    "uuid": "a08d29fb-4d69-49eb-81c3-004e151d39c0",
    "summary": "香港法院星期一（10月30日）撤销针对一名美国地方议员的无牌持枪控状，但对被告执行自签担保守行为令，长达24个月。综合星岛头条、法新社、香港01和《明报》报道，美国华盛顿州参议员威..."
  },
  {
    "title": "浙江开通首条墨西哥全货机航线",
    "link": "/realtime/china/story20231030-1446642",
    "uuid": "1a5bdf90-8211-4c5a-b1b4-f8351d1042a0",
    "summary": "浙江开通首条墨西哥全货机航线，一周将有三趟往返航班。据澎湃新闻星期一（10月30日）报道，来自墨西哥的A330全货机满载约54吨跨境电商等货物，星期天（29日）晚从杭州萧山国际机场..."
  },
  {
    "title": "博鳌亚洲论坛2024年年会计划于3月在海南举办",
    "link": "/realtime/china/story20231030-1446650",
    "uuid": "109acb41-4ab7-42a9-b3a2-7c768a02ee03",
    "summary": "博鳌亚洲论坛理事长潘基文宣布，博鳌亚洲论坛2024年年会计划于2024年3月26日到29日在海南博鳌举办。据央视网报道，博鳌亚洲论坛全球经济发展与安全论坛第二届大会星期一（10月3..."
  },
  {
    "title": "蓝白政党协商共同声明提重启两岸对话 没提总统人选",
    "link": "/realtime/china/story20231030-1446648",
    "uuid": "7ee97d09-1c14-4801-8267-72f054198c72",
    "summary": "台湾在野阵营的蓝白政党协商星期一（10月30日）登场，国民党主席朱立伦、民众党主席柯文哲经过一个半小时的会谈后，双方召开记者会并发表共同声明，其中提到重启两岸对话，但对于蓝白合总统..."
  },
  {
    "title": "恒大在香港的清盘呈请聆讯再度押后",
    "link": "/realtime/china/story20231030-1446641",
    "uuid": "9cc6c2f7-6946-45ab-9a09-8a57f23ce638",
    "summary": "中国房地产巨头恒大集团的清盘呈请聆讯再次押后至12月4日。此前香港法院已数度将恒大的清盘呈请聆讯押后，但恒大历时漫长的重组之路仍未见明确转机。彭博社星期一（10月30日）上午报道上..."
  },
  {
    "title": "崔天凯：美国所谓“中国问题专家”往往是“半瓶子醋”",
    "link": "/realtime/china/story20231030-1446636",
    "uuid": "1aa3efa0-56e9-4d76-857b-a5cfe2e8def5",
    "summary": "中国前驻美国大使崔天凯说，美国一些所谓的“中国问题专家”往往是“半瓶子醋”，这其实很危险，因为别人以为他们是专家，但他们讲出来的话却是误导。据中国官媒《环球时报》报道，崔天凯星期天..."
  },
  {
    "title": "蓝白政党协商登场 朱立伦柯文哲握手致意",
    "link": "/realtime/china/story20231030-1446628",
    "uuid": "07ba5141-a68d-4970-aef6-99345d8b10f1",
    "summary": "台湾在野阵营的蓝白整合进入政党协商阶段，首场党对党会议星期一（10月30日）登场。国民党主席朱立伦、民众党主席柯文哲在会前先进行合影与握手致意，并发表简短谈话。柯文哲表示，盼会谈能..."
  },
  {
    "title": "拱北海关原关长周斌被查",
    "link": "/realtime/china/story20231030-1446624",
    "uuid": "2dd3b176-c3f6-45c6-a5ae-f0e7a9d3fcc7",
    "summary": "拱北海关原党组书记、关长周斌涉嫌严重违纪违法被查。据中央纪委国家监委网站星期一（10月30日）通报，中央纪委国家监委驻海关总署纪检监察组、辽宁省纪委监委消息称，拱北海关原党组书记、..."
  },
  {
    "title": "苏州学生举日本国旗引争议 区教育局促全区学校举一反三",
    "link": "/realtime/china/story20231030-1446623",
    "uuid": "0674becf-850e-4b76-b886-53c39cba811b",
    "summary": "针对苏州一所学校运动会上有学生举日本国旗，区教育局回应时重申，这是学生在模拟亚运会入场方式，并已督促全区学校举一反三，避免类似事件再次发生。苏州市吴江区教育局星期星期天（10月29..."
  },
  {
    "title": "中共中央军委副主席张又侠批个别国家蓄意制造动荡",
    "link": "/realtime/china/story20231030-1446621",
    "uuid": "be8405f5-9162-4090-ab67-e2814fdbeb86",
    "summary": "中共中央军委副主席张又侠星期一（10月30日）不点名批评美国称，个别国家蓄意制造动荡，并且人为制造很多地缘矛盾，长期拉偏架，导致地区局势复杂难解。张又侠是在第十届北京香山论坛开幕式..."
  },
  {
    "title": "北大校报发文缅怀李克强：师生沉浸在深深悲痛中",
    "link": "/realtime/china/story20231030-1446616",
    "uuid": "52a6b49c-326f-4363-9bbe-e553d89a21bd",
    "summary": "中国前总理李克强因突发心脏病于上星期五（10月27日）凌晨逝世，他的母校北京大学旗下报纸《北京大学校报》发文缅怀，并重发李克强早年在校学习、工作的报纸剪报。《北京大学校报》星期天（..."
  },
  {
    "title": "港媒：“黑码”健康申报最快11月1日取消",
    "link": "/realtime/china/story20231030-1446615",
    "uuid": "0d7af6f4-52aa-4fc4-a0e1-9fa0878b4361",
    "summary": "香港媒体报道，全国人大常委李慧琼引述中国大陆海关总署称，取消黑码正在审批最后阶段，有信心星期三（11月1日）起取消。中国大陆出入境健康申报被俗称为“黑码”。据《明报》报道，记者星期..."
  },
  {
    "title": "【视频】俄罗斯防长绍伊古出席北京香山论坛",
    "link": "/realtime/china/story20231030-1446614",
    "uuid": "9064c1df-e4d3-4c70-9eea-7ec14bafa72e",
    "summary": "北京香山论坛星期一（10月30日）上午开幕，中共中央军委副主席张又侠出席开幕式。俄罗斯防长绍伊古参加论坛，在论坛开幕前与张又侠并肩步入会场。 北京香山论坛星期一（10..."
  },
  {
    "title": "中国驻日使馆促G7勿对日本水产禁令采双重标准",
    "link": "/realtime/china/story20231030-1446613",
    "uuid": "b0676894-705c-480c-8aeb-a6d9973caaf9",
    "summary": "针对七国集团（G7）呼吁撤销对日本海产进口限制，中国驻日本大使馆回应称，作为问题制造者的日本应纠正排海错误行径，并敦促七国集团不要坚持双重标准。根据中国驻日本大使馆官方微信公众号星..."
  },
  {
    "title": "深圳过山车事故28人受伤 伤者比首次通报多20人",
    "link": "/realtime/china/story20231030-1446610",
    "uuid": "a4757a19-1a8c-4ad5-8a8f-dd0639934204",
    "summary": "中国深圳欢乐谷主题乐园发生过山车相撞事故后，深圳南山区官方最新通报，事故已致28人受伤，伤者比欢乐谷首次通报多了20人。深圳南山区安全管理委员会办公室星期天（10月29日）晚上通过..."
  },
  {
    "title": "中国多省辟谣推行“工龄退休”",
    "link": "/realtime/china/story20231030-1446608",
    "uuid": "8e8d8586-ed44-4d8f-aa1a-a7e49901720c",
    "summary": "中国多省份辟谣推行“工龄退休”的网络传闻，并称将严格执行中国国家统一规定的退休政策。河北省人社厅微信公众号上星期六（10月28日）发布声明称，一篇名为《人社部：2024年1月1日起..."
  },
  {
    "title": "以哈冲突之际 中国海军结束对卡塔尔访问",
    "link": "/realtime/china/story20231030-1446607",
    "uuid": "35714239-acaf-48cd-89fa-9df791641b8a",
    "summary": "在以哈冲突导致中东局势升温之际，中国海军上周结束了对卡塔尔的访问。新华社星期天（10月29日）报道，中国海军第44批护航编队结束了对卡塔尔的访问，于上星期六（10月28日）下午离开..."
  },
  {
    "title": "神舟十六号航天员完成交接周二返回地球",
    "link": "/realtime/china/story20231030-1446605",
    "uuid": "065a66ce-7327-44ff-9b12-0f782f31e2e5",
    "summary": "中国神舟十六号航天员乘组已经与神舟十七号航天员乘组进行交接仪式，并将在星期二（10月31日）返回地球。据中国央视新闻报道，神舟十六号、神舟十七号航天员乘组星期天（29日）进行交接仪..."
  },
  {
    "title": "何立峰已出任中共中央财办主任",
    "link": "/realtime/china/story20231030-1446604",
    "uuid": "6ee72ef2-a192-487e-a838-ac853708c030",
    "summary": "中共政治局委员、中国副总理何立峰已出任中共中央财经委员会办公室主任。据新华社报道，何立峰星期天（10月29日）下午以中共政治局委员、中央财办主任的身份，在北京会见法国总统外事顾问博..."
  },
  {
    "title": "中美航线票价有望进一步下降",
    "link": "/realtime/china/story20231029-1446508",
    "uuid": "07e2f22e-ed72-42ec-8064-a20d1d65cdc8",
    "summary": "美国允许中国航司在11月9日起进一步增加每周增班后，中美航线票价有望进一步下降。根据美国交通部官网，美国交通部在当地时间星期五（10月27日）发布最新通知称，从11月9日起，允许中..."
  },
  {
    "title": "香港整体航班升降量恢复至疫情前七成",
    "link": "/realtime/china/story20231029-1446497",
    "uuid": "d6bc7cc3-99b5-415f-963c-d510330abbf7",
    "summary": "香港特区政府运输及物流局局长林世雄说，香港国际机场的每日客运量预计会在明年完全恢复，而整体航班升降量在今年首九个月恢复至冠病疫情前的七成，航点数量则约为疫情前的八成。根据香港中通社..."
  },
  {
    "title": "中联部副部长率团访所罗门群岛",
    "link": "/realtime/china/story20231029-1446494",
    "uuid": "6e9cab89-0460-485a-856a-12da26157c64",
    "summary": "中共中央对外联络部副部长郭业洲率团访问南太平洋岛国所罗门群岛三天，期间与所罗门群岛“我们的党”领袖、总理索加瓦雷会面。根据新华社，郭业洲星期五（10月27日）至星期天（29日），率..."
  },
  {
    "title": "港财政司长称撤离的外企已陆续回港",
    "link": "/realtime/china/story20231029-1446490",
    "uuid": "fd8f70c6-8ddf-4b19-a822-e99472ba5e48",
    "summary": "香港财政司司长陈茂波称，疫情期间将区域总部迁出香港的外资企业，已陆续返回香港。据网媒“香港01”报道，陈茂波星期天（10月29日）在电台节目上说，疫情期间香港出入境受限制，特别是去..."
  },
  {
    "title": "郭台铭称向妈祖祈求两岸和平、抗经济危机、要团结避战",
    "link": "/realtime/china/story20231029-1446492",
    "uuid": "0eb31a48-4e09-4580-84bf-e21737c9d63d",
    "summary": "台湾鸿海集团创办人郭台铭星期天（10月29日）在庙宇活动上致词时说，他向妈祖祈求两岸能和平、抗经济危机，并且要团结避战。据台湾壹苹新闻网报道，准备独立参选台湾总统的郭台铭在新北市参..."
  },
  {
    "title": "朱立伦证实将与柯文哲面对面协商",
    "link": "/realtime/china/story20231029-1446520",
    "uuid": "a1c0cd98-5837-43e2-b980-d5b7f35e2b4c",
    "summary": "台湾在野阵营的“蓝白合”正式进入政党协商阶段。国民党主席朱立伦星期天（10月29日）证实，星期一（30日）将和民众党总统参选人柯文哲进行面对面协商。台湾《联合报》星期天凌晨报道，蓝..."
  },
  {
    "title": "楼价若大涨会否重新“加辣”？港特首：不评估未发生事情",
    "link": "/realtime/china/story20231029-1446507",
    "uuid": "cbf5a3f9-23c2-4e9c-b440-3f408dfe64a2",
    "summary": "香港特首李家超强调，港府的角色不是决定楼价。至于日后楼价如果大涨时，香港是否会重新“加辣”（收紧管控力度），李家超回应时说，不会评估未发生的事情。综合香港《明报》和无线新闻报道，李..."
  },
  {
    "title": "中国智库专家：须以良法善治提升民企长期信心",
    "link": "/realtime/china/story20231029-1446511",
    "uuid": "2d4a8b1d-e5be-4cb8-b5d1-4d33bdcecbe0",
    "summary": "中国国家创新与发展战略研究会副理事长、中国发展研究院院长王彤认为，提振民营经济信心时，要重视制度和法律制度的作用，必须以良法善治提升民营经济的长期信心。据上海证券报报道，王彤星期天..."
  },
  {
    "title": "哈尔滨一居民家液化气爆炸致一死四伤",
    "link": "/realtime/china/story20231029-1446503",
    "uuid": "8a4bd01a-02ab-45d4-be5b-a82fa53330aa",
    "summary": "黑龙江省哈尔滨市一户居民家中发生液化气爆炸，造成一人死亡、四人受伤。据中国央视新闻报道，记者从哈尔滨市道外区委宣传部了解到，星期天（10月29日）早晨6时39分，哈尔滨市道外区团结..."
  },
  {
    "title": "韩国瑜称男支持者摄护腺肿大 陈其迈：不要随便开玩笑",
    "link": "/realtime/china/story20231029-1446512",
    "uuid": "bf214bc5-6d57-48b6-9b95-006afe7af41d",
    "summary": "对于前台湾高雄市长韩国瑜将自己的支持者比喻为“男的都摄护腺肿大、女的都过了更年期”，现任高雄市长陈其迈说，不论是疾病或生理现象，在选举期间，不要随便开玩笑。综合《联合报》和《自由时..."
  },
  {
    "title": "陈茂波预计香港第三季度GDP增速慢于预期",
    "link": "/realtime/china/story20231029-1446502",
    "uuid": "95f6d26c-2f98-4637-915b-f989cedd9bf5",
    "summary": "香港财政司长陈茂波预计，受地缘政治紧张局势加剧等多方面外部因素影响，香港第三季度生产总值（GDP）增速将慢于预期。陈茂波星期天（10月29日）发表网志称，香港经济自今年起稳步复苏，..."
  },
  {
    "title": "恒大恐成香港史上最大地产商清盘案",
    "link": "/realtime/china/story20231029-1446482",
    "uuid": "cc5952b4-b4e8-41fb-9309-b2ff009fe6d8",
    "summary": "中国恒大星期一（10月30日）将在香港高等法院面临清盘呈请聆听，一旦颁令清盘，恒大将成香港法律史上遭遇清盘的最大型地产开发商，并可能再次严重打击大陆房地产市场。据彭博社报道，早前一..."
  },
  {
    "title": "巴基斯坦人民币清算行业务正式启动",
    "link": "/realtime/china/story20231029-1446474",
    "uuid": "fa5e07d2-4404-42aa-8b3b-f1b5879ba0be",
    "summary": "巴基斯坦人民币清算行在首都伊斯兰堡开业。开业仪式星期五（10月27日）在伊斯兰堡举行，标志着巴基斯坦人民币清算行业务正式启动。据新华社报道，巴基斯坦看守政府财政部长沙姆沙德·阿赫塔..."
  },
  {
    "title": "柯文哲朱立伦据报星期一展开政党协商",
    "link": "/realtime/china/story20231029-1446487",
    "uuid": "17169231-2b3d-46e2-aefe-6e681a166f07",
    "summary": "台湾在野阵营的蓝白整合进入政党协商阶段，据报国民党主席朱立伦和民众党主席柯文哲预计星期一（10月30日）将进行第一次的面对面协商。不过，柯文哲星期天（29日）没有正面回应，他仅说“..."
  },
  {
    "title": "港发展局将公布《北部都会区行动纲领》",
    "link": "/realtime/china/story20231029-1446475",
    "uuid": "55ee4baa-cec4-4c3f-ad39-9b348d88f712",
    "summary": "香港发展局将于星期一（10月30日）公布《北部都会区行动纲领》，说明各区推进的项目及时间表。据《明报》报道，港发展局称，北部都会区将划为四大区域，以“产业带动，基建先行”为主轴，成..."
  },
  {
    "title": "中国原驻美大使崔天凯：中美若躺平或发生最不希望的事",
    "link": "/realtime/china/story20231029-1446481",
    "uuid": "5e10638d-0f4e-4f88-bf43-f5874ac29adc",
    "summary": "中国原驻美大使崔天凯认为，中美两国如果发生冲突对抗，对世界肯定是灾难性的，但这不意味着中美在“躺平”的状态下，就可以自动避免这种最坏情况的发生。中美如果躺平，可能会发生最不希望的事..."
  },
  {
    "title": "苏州学生举日本国旗 校方：模拟亚运会入场式",
    "link": "/realtime/china/story20231029-1446471",
    "uuid": "b4bd328e-6be2-4fa1-b6ef-49fa0e5d8b30",
    "summary": "对于网络上流传的“学生运动会举日本国旗”一事，苏州市吴江区横扇学校称，这是学生在模拟亚运会入场式。据澎湃新闻报道，横扇学校星期六（10月28日）晚回应称，10月27日上午，该校小学..."
  },
  {
    "title": "日防卫省：中国航母山东舰在太平洋航行",
    "link": "/realtime/china/story20231029-1446466",
    "uuid": "a235de1c-8547-4fe0-ba72-301db0db7c1a",
    "summary": "日本防卫省称，中国航母山东舰在太平洋航行，舰载机进行了起降。据日本共同社报道，日本防卫省统合幕僚监部星期六（10月28日）发布消息称，发现中国海军航母山东舰当天上午7点前后，在冲绳..."
  },
  {
    "title": "中国民航局：正编制文件进一步加强重要数据保护",
    "link": "/realtime/china/story20231029-1446473",
    "uuid": "48177933-a380-46ee-8921-6cdf15eb4867",
    "summary": "针对有网民留言反映订购机票后旅客信息遭泄露，中国民用航空局回应称，正在编制相关文件，进一步加强对重要数据的保护。据中国澎湃新闻星期天（10月29日）报道，有网民通过人民网领导留言板..."
  },
  {
    "title": "港财政司长：市场调整楼价是合适做法",
    "link": "/realtime/china/story20231029-1446467",
    "uuid": "a62579f3-81c9-499c-b00a-97397302404c",
    "summary": "香港财政司司长陈茂波认为，只要不造成金融系统安全隐患，楼价由市场调整是合适做法。陈茂波星期天（10月29日）在香港商业电台节目上说，香港仍要持续增加土地，以增加房屋供应，支持招商引..."
  },
  {
    "title": "美国蒙大拿州州长访台",
    "link": "/realtime/china/story20231029-1446470",
    "uuid": "ee9048d2-d7f1-4560-a8fa-596dd0b03c3e",
    "summary": "美国蒙大拿州州长詹福尔特率团访问台湾，将与台湾总统蔡英文会面。据台湾外交部官网星期天（10月29日）发布的新闻稿，詹福尔特（Greg Gianforte）伉俪于10月29日至11月..."
  },
  {
    "title": "哈尔滨公司规定私聊微信罚款被要求纠正",
    "link": "/realtime/china/story20231029-1446465",
    "uuid": "9899eb99-c649-428b-b3ce-98c2eaa6c278",
    "summary": "中国黑龙江哈尔滨一家公司规定，员工工作时间私聊微信要缴纳罚款，且每月累计超过五次会被辞退。对此，当地人力资源和社会保障局通报称，已要求该企业立即纠正。据上游新闻星期天（10月29日..."
  },
  {
    "title": "中国纪检监察机关1至9月处分省部级干部人数同比少14人",
    "link": "/realtime/china/story20231029-1446463",
    "uuid": "5f77db3f-c376-4cf3-9c72-9d0b8a174aa8",
    "summary": "官方数据显示，中国的纪检监察机关今年首九个月已针对34名省部级干部进行处分，同比减少14人。中共中央纪委国家监委网站星期天（10月29日）在微信公众号上公布，2023年1月至9月全..."
  },
  {
    "title": "续签被拒 加籍港中大历史系副教授被校方解雇",
    "link": "/realtime/china/story20231029-1446462",
    "uuid": "902eb64a-502f-4044-bcc2-2d8a1e034e07",
    "summary": "加拿大籍华裔历史学者、香港中文大学历史系副教授何晓清因申请工作签证返港被拒，被香港中文大学解雇。据网媒“香港01”报道，前香港专上学生联会委员陈清华星期六（10月28日）在脸书发文..."
  }
]
