[
  {
    "title": "历经多次争议 民众党好感度落后蓝绿两党",
    "link": "/realtime/china/story20230803-1420167",
    "uuid": "6366ceb3-3a43-4add-b181-460bf4dbb6db",
    "summary": "经历了多次失言和争议后，台湾民众党的网络好感度落后于民进党和国民党。《TPOC台湾议题研究中心》星期三（8月2日）在官网公布网络舆情数据分析结果，显示民众党最近一个月有两波声量高峰..."
  },
  {
    "title": "澳贸易部长：中国料将在数天内确定对澳大麦惩罚性关税评估结果",
    "link": "/realtime/china/story20230803-1420164",
    "uuid": "4bdec9f6-b557-4cf9-9da1-763d9fa91979",
    "summary": "澳大利亚贸易部长法雷尔说，澳洲预料将在几天内得悉中国对澳大麦实施惩罚性关税的评估结果，这将是中澳关系改善的最新迹象。据彭博社报道，中国此前对澳洲大麦实施惩罚性关税进行为期四个月的评..."
  },
  {
    "title": "美台贸易倡议法案送白宫 麦卡锡：支持台湾首步",
    "link": "/realtime/china/story20230803-1420149",
    "uuid": "f866d9ea-5bbb-4a58-bc2c-4abe1d8dc0af",
    "summary": "美国众议院议长麦卡锡签署美国国会日前通过的美台21世纪贸易倡议首批协定实施法案后，已移送白宫，等待总统拜登签署生效。麦卡锡说，这成为美众议院共和党人持续支持台湾人民的第一步。据美国..."
  },
  {
    "title": "中国解放军东部战区在东海开展实兵实弹操练",
    "link": "/realtime/china/story20230803-1420148",
    "uuid": "edcbe6ae-bc15-487b-b604-a2575f9ea95f",
    "summary": "中国人民解放军东部战区海军近日在东海海域开展实兵实弹操练。据“东部战区”官方微博账号星期四（8月3日）消息，近日，东部战区海军某驱逐舰支队厦门舰、扬州舰、滨州舰等舰艇组成编队，赴东..."
  },
  {
    "title": "台中科院九鹏基地传爆炸事故 四人重伤",
    "link": "/realtime/china/story20230803-1420130",
    "uuid": "d0b43de3-935f-406d-a4e9-a108e94bf6a8",
    "summary": "台湾中山科学院位于屏东的九鹏基地星期四（8月3日）发生爆炸事故，造成四人严重烧烫伤。据台湾《自由时报》报道，中科院星期四早上通报，九鹏基地内多名人员在进行余料销毁时，突然发生大规模..."
  },
  {
    "title": "遭通缉海外港人袁弓夷亲人再被国安处带走问话",
    "link": "/realtime/china/story20230803-1420145",
    "uuid": "9350c448-c4ad-474a-91e9-7d19b5f89370",
    "summary": "“香港议会”发起人袁弓夷在香港的亲人再被香港警方国安处带走问话。综合《星岛日报》和网媒“香港01”引述消息人士报道，香港警方国安处星期四（8月3日）约见袁弓夷第二任妻子和她所生儿子..."
  },
  {
    "title": "中国拟规定过百万个人信息处理者每年审计至少一次",
    "link": "/realtime/china/story20230803-1420135",
    "uuid": "8fc26aea-92f0-45fd-90d6-4bacd2790f0f",
    "summary": "中国官方拟对个人信息保护做出新规定，要求处理超过100万人个人信息的个人信息处理者，每年至少开展一次个人信息保护合规审计。中国国家互联网信息办公室星期四（8月3日）在官网公布，网信..."
  },
  {
    "title": "恒大物业今在港交所复牌 股价一度暴跌近50%",
    "link": "/realtime/china/story20230803-1420124",
    "uuid": "19d7d314-d703-49bd-bbb7-8c272a3a6e9b",
    "summary": "恒大物业股票星期四（8月3日）早上9时在香港证券交易所恢复买卖。复牌首日，恒大物业港股一度暴跌49.57%。恒大物业星期三（2日）晚间发布公告，称履行复牌指引，公司股票将在8月3日..."
  },
  {
    "title": "中国房企旭辉集团主席等人据报减价卖在港洋房",
    "link": "/realtime/china/story20230803-1420128",
    "uuid": "22da9202-8b6a-4ed5-8f9b-6990a713f9ca",
    "summary": "香港媒体报道，中国房地产企业旭辉集团主席林中等人降价出售在港洋房。香港经济日报星期四（8月3日）引述消息人士报道，旭辉集团主席林中及相关人士，近日调低赤柱五幢洋房售价约16%，至逾..."
  },
  {
    "title": "香港7月标普全球PMI降至49.4 今年私营经济首现收缩",
    "link": "/realtime/china/story20230803-1420123",
    "uuid": "9c82866d-a955-451a-a2a0-01e4bd39a9b8",
    "summary": "标普全球7月香港采购经理指数（PMI）经季节调整后，跌穿50.0持平点，显示私营经济今年首次缩减经营活动。综合香港经济日报和彭博社星期四（8月3日）报道，香港7月标普全球PMI指数..."
  },
  {
    "title": "卡努台风登陆台湾北部 四县市宣布停班停课",
    "link": "/realtime/china/story20230803-1420120",
    "uuid": "6e3b208e-5a1e-405a-b263-32143a828be7",
    "summary": "今年第6号台风“卡努”登陆台湾北部，台北、新北、基隆和宜兰四个县市星期四（8月3日）停班停课，近40个台湾国际航班被取消。综合台湾《上报》《联合报》《自由时报》等报道，台湾中央气象..."
  },
  {
    "title": "美国务院对中国吁全社会反间防谍表达关切",
    "link": "/realtime/china/story20230803-1420113",
    "uuid": "26bbd0e9-64e1-4dc7-a292-e328947bfb6d",
    "summary": "美国政府对中国国家安全部呼吁全社会反间防谍表达关切。据路透社报道，美国国务院发言人米勒星期三（8月2日）在例行记者会上，作出以上表述，并称美国将密切关注北京如何实施经修订后的《反间..."
  },
  {
    "title": "中国公安部发布高质量发展26条措施 为外籍人员提供签证便利",
    "link": "/realtime/china/story20230803-1420112",
    "uuid": "3119c311-995d-430a-951d-cfbbf558e554",
    "summary": "中国公安部发布公安机关服务保障高质量发展26条措施，其中包括试点实施灵活落户政策，为外籍商贸人员提供多次签证换发便利。据新华社报道，中国公安部星期四（8月3日）召开新闻发布会，发布..."
  },
  {
    "title": "7月财新中国服务业PMI略升 经营活动维持韧性",
    "link": "/realtime/china/story20230803-1420111",
    "uuid": "0e96053a-5c7c-4604-84d0-23a85b0d238c",
    "summary": "7月财新中国服务业经营活动指数（PMI）略有回升，显示经营活动仍维持韧性。据财新网报道，8月3日公布的7月财新中国通用服务业PMI录得54.1，比6月的53.9略升0.2个百分点。"
  },
  {
    "title": "美国防高官与中国外交官商讨中美国防事务",
    "link": "/realtime/china/story20230803-1420105",
    "uuid": "41da94fe-17ea-4be6-9d08-5a0d4aa3faf5",
    "summary": "美国五角大楼发言人通报，负责亚洲事务的美国国防高官和中国外交官商讨中美国防事务。这是中美国安高官罕见的高层对话。据路透社报道，美国五角大楼发言人星期三（8月2日）发布声明说，“美国..."
  },
  {
    "title": "华科大研究团队称初步复现韩国超导晶体",
    "link": "/realtime/china/story20230803-1420101",
    "uuid": "794346ff-5e58-427e-820d-d5cacc000a7e",
    "summary": "韩国科学团队宣布成功合成世界首个室温常压超导晶体后，中国一所大学的研究团队也宣布初步复现这一超导材料。中国线上视频平台哔哩哔哩动画（B站）UP主“关山口男子技师”星期二（8月1日）..."
  },
  {
    "title": "郑雁雄吁香港各界全力支持香港由治及兴、以变促兴",
    "link": "/realtime/china/story20230803-1420097",
    "uuid": "8739468c-82e9-4751-b6e7-d96861ccaf2a",
    "summary": "香港中联办主任郑雁雄说，世界目前正面临百年未有之大变局，香港身处其中，期盼各界全力支持香港由治及兴、以变促兴。据香港中联办官网消息，郑雁雄星期三（8月2日）在香港举行的“激发香港‘..."
  },
  {
    "title": "佩洛西发表访台一周年声明：美对台承诺坚若磐石",
    "link": "/realtime/china/story20230803-1420095",
    "uuid": "16cf12df-2ee1-4524-b3f7-5b6d6b0e1878",
    "summary": "美国前众议院议长佩洛西在访问台湾一周年之际发表声明，强调美国在台湾和全世界对自由和人权作出的承诺仍坚若磐石。佩洛西办公室官网星期四（8月3日）发表了一份声明，以纪念佩洛西访问台湾一..."
  },
  {
    "title": "美或拒请李家超出席APEC 港政界批公器私用",
    "link": "/realtime/china/story20230803-1420093",
    "uuid": "a8e645b4-21ac-47a2-904a-4a2ba35b7d19",
    "summary": "美国或将不邀请香港特首李家超出席今年11月在旧金山举行的亚太经济合作组织峰会（APEC）。香港政界人士及政党团体星期三（8月2日）批评美方行为公器私用。综合香港中通社和网媒“香港0..."
  },
  {
    "title": "中国两名蓝天救援队员在救灾行动中遇难",
    "link": "/realtime/china/story20230803-1420090",
    "uuid": "3ed62378-b33a-4c6c-b75c-f434be2334e5",
    "summary": "中国各地汛情救灾行动开展之际，北京市和福建泉州市各有一名蓝天救援队队员在救灾行动中遇难。“北京房山”微信公众号星期三（8月2日）通报，四名北京市房山区蓝天救援队队员在班各庄大桥开展..."
  },
  {
    "title": "中国商务部批美将两中企列强迫劳动预防法实体清单",
    "link": "/realtime/china/story20230803-1420087",
    "uuid": "24a209a4-478f-4f00-b7c2-015db87ee10e",
    "summary": "中国商务部指美国以强迫劳动课题为由，禁止两家中国企业的产品是典型的经济胁迫行为，誓言将采取必要措施，坚定维护中国企业合法权益。商务部星期三（8月2日）在官网上说：“美方宣布将两家中..."
  },
  {
    "title": "郭台铭：台海若发生战争 只要10秒华尔街股市就崩盘",
    "link": "/realtime/china/story20230803-1420084",
    "uuid": "8e1b8afa-4ba8-47c4-b5d5-9c907083b989",
    "summary": "台湾鸿海创办人郭台铭星期三（8月2日）在社交平台发文认为，台海若发生战争，只要10秒钟，华尔街股市就会崩盘。郭台铭在脸书写道，他在访问美国期间，与作家弗里德曼（Thomas Fri..."
  },
  {
    "title": "下午察：北京雨停之后",
    "link": "/realtime/china/story20230802-1420050",
    "uuid": "c0b63c52-54f9-4b51-b004-078a40427cfd",
    "summary": "经过了持续四天、70个小时的强降雨，北京终于在星期三（8月2日）上午7时30分解除暴雨黄色预警，华北地区这轮降水也接近尾声。雨虽然停了，但河北涿州等地的洪水灾情还在延续，截至星期二..."
  },
  {
    "title": "瑞幸咖啡上半年营收超百亿人民币",
    "link": "/realtime/china/story20230802-1419942",
    "uuid": "40a0f7aa-c12a-4d15-bb8e-a45693d83ead",
    "summary": "中国本土连锁咖啡品牌瑞幸咖啡今年上半年累计营收超过100亿元（人民币，下同，约19亿新元），较去年同期转亏为盈。据澎湃新闻报道，瑞幸咖啡星期二（8月1日）公布的二季度财报显示，受到..."
  },
  {
    "title": "杭州市将取消积分落户名额限制",
    "link": "/realtime/china/story20230802-1419926",
    "uuid": "8af9699b-835b-4771-ab73-989425fd02e8",
    "summary": "继浙江省取消省内大部分地区落户限制后，省会杭州市也进一步放宽落户限制，包括取消积分落户名额限制等，加大“抢人”力度。据浙江日报集团旗下“潮新闻”报道，浙江省政府办公厅星期一（7月3..."
  },
  {
    "title": "港机管局主席：机场客运量预计明年底前完全恢复",
    "link": "/realtime/china/story20230802-1419784",
    "uuid": "fa81b539-ce3d-49ab-b081-b858a1262f02",
    "summary": "香港机管局主席苏泽光说，香港机场客运量至今已回复至疫情前约六成，预计明年底前完全恢复。据星岛日报报道，苏泽光星期三（8月2日）在香港国际机场出席“国际航空论坛2023”活动。他说，..."
  },
  {
    "title": "朱立伦称侯友宜民调追上柯文哲 国民党：不会对外公布",
    "link": "/realtime/china/story20230802-1419785",
    "uuid": "ba9097ed-da2a-45fe-9443-cd8469df3917",
    "summary": "国民党主席朱立伦引用内参民调称国民党总统参选人侯友宜已超越民众党参选人柯文哲，国民党发言人说，内参民调仅供内部参考，不会对外公布。据台湾中央社报道，侯友宜民调状况持续低迷，前高雄市..."
  },
  {
    "title": "中国官方示警：8月南北多地洪涝灾害风险高",
    "link": "/realtime/china/story20230802-1419778",
    "uuid": "f45cf5c7-d595-44c7-826f-5a62a33767a5",
    "summary": "中国官方发布的8月份全国自然灾害风险形势显示，南北多地洪涝灾害风险较高。中国应急管理部官网星期三（8月2日）发布消息，国家减灾委员会办公室、应急管理部近日会同自然资源部、住房和城乡..."
  },
  {
    "title": "香港7月异常炎热 平均最高温达33摄氏度",
    "link": "/realtime/china/story20230802-1419952",
    "uuid": "67d1e4db-4bab-497e-a8e3-5a18eabfd531",
    "summary": "香港今年7月异常炎热，平均最高气温33摄氏度、平均气温30.1摄氏度、平均最低气温28摄氏度，分别较其各自正常值高1.4度、1.2度及1.1度，皆是有纪录以来7月的第三高。香港政府..."
  },
  {
    "title": "北京气象局：本次降雨为140年来北京最大降雨",
    "link": "/realtime/china/story20230802-1419940",
    "uuid": "85cf863e-b7c6-4816-b2b4-58aeb37d06ba",
    "summary": "台风“杜苏芮”造成北京、天津、河北等地强降水，北京气象局称，本次降雨为140年来北京的最大降雨。据北京气象局官方微博星期三（8月2日）消息，本次北京的强降雨天气过程中，记录到的降雨..."
  },
  {
    "title": "台外长：中国大陆对台动武将带来灾难性后果",
    "link": "/realtime/china/story20230802-1419953",
    "uuid": "ea4eab39-db29-4d0d-848e-7133cab52a40",
    "summary": "台湾外交部长吴钊燮称，台湾对全球半导体产业和全球航运具有战略意义，中国大陆武力攻打台湾将给世界带来灾难性的后果。他也坦言，台湾并不指望美国为他们打一场战争。吴钊燮星期三（8月2日）..."
  },
  {
    "title": "朱立伦：亲美、友日、和陆是国民党坚定在走的路",
    "link": "/realtime/china/story20230802-1419925",
    "uuid": "87d2bc1e-ae7f-4708-9fdf-0e38c0dbde5c",
    "summary": "国民党总统参选人侯友宜访日，党主席朱立伦说，“亲美、友日、和陆”是国民党坚定在走的路。据联合新闻网报道，朱立伦星期三（8月2日）在中常会上说，此次访日，看到侯友宜的国际观与维护台海..."
  },
  {
    "title": "李铁涉嫌受贿行贿等案被提起公诉",
    "link": "/realtime/china/story20230802-1419939",
    "uuid": "b2f36f24-b8e1-45d1-b665-eeaf5148bfb3",
    "summary": "中国国家足球队原主帅李铁涉嫌受贿、对非国家工作人员行贿等案件，被检方提起公诉。据央视新闻星期三（8月2日）报道，李铁涉嫌受贿、行贿、单位行贿、非国家工作人员受贿、对非国家工作人员行..."
  },
  {
    "title": "佳木斯拟建方舱？官方回应：实建文旅宾馆类项目",
    "link": "/realtime/china/story20230802-1419800",
    "uuid": "49780cf2-27b5-4929-99d7-dfa902934205",
    "summary": "对于网传黑龙江省佳木斯市一居民区内要建方舱医院，当地政府部门回应称，之前的专项资金没有花完，实际上建造的是文旅、宾馆类项目。综合澎湃新闻、华龙网报道，在佳木斯市经营一家杂货店的杨先..."
  },
  {
    "title": "中国跌出美加州教师养老金基金12大配置国排行榜",
    "link": "/realtime/china/story20230802-1419931",
    "uuid": "27cddc9e-4fcc-4fb5-adf8-5e78392d1a0a",
    "summary": "以国家资产敞口计算，中国已跌出美国加州教师养老金基金（CalSTRS）12大配置国家的排行榜外。彭博社星期三（8月2日）报道，根据CalSTRS基于市值和收入敞口的最新披露，截至5..."
  },
  {
    "title": "朱立伦宣布启动立委总统参选人二合一造势计划",
    "link": "/realtime/china/story20230802-1419928",
    "uuid": "7847de31-d49c-4385-97f7-c8cb6805e549",
    "summary": "国民党主席朱立伦宣布在全台各个城市启动总统、立委参选人二合一造势计划。综合台湾风传媒和中央社报道，朱立伦星期三（8月2日）在国民党中常会上说，国民党7月23日举行全台党代表大会后，..."
  },
  {
    "title": "顺丰控股将在香港二次上市",
    "link": "/realtime/china/story20230802-1419914",
    "uuid": "44e3164c-2833-4dff-984d-39142da2d00d",
    "summary": "中国快递巨头顺丰控股宣布，将选择适当时机在港交所挂牌发行上市，坐实此前公司将赴香港IPO的传闻。据上海证券报报道，顺丰控股星期二（8月1日）晚间公告称，为进一步推进公司国际化战略，..."
  },
  {
    "title": "韩国称合成首个室温常压超导体 中国概念股暴涨",
    "link": "/realtime/china/story20230802-1419911",
    "uuid": "4427face-c641-48bf-878a-80462eeb355d",
    "summary": "韩国科学团队日前称实现在室温常压环境下合成超导体后，尽管国际学界还抱持怀疑态度，但仍带动中国相关的超导体概念股暴涨。据彭博社报道，韩国量子能源研究中心的团队7月22日在论文预印本网..."
  },
  {
    "title": "台总统府：蔡英文快筛阴性后恢复良好 没有后遗症",
    "link": "/realtime/china/story20230802-1419795",
    "uuid": "48289074-0353-451c-8f18-91c827efc11b",
    "summary": "此前确诊冠病的台湾总统蔡英文快筛阴性后恢复良好，没有出现后遗症。据台湾中央社报道，台总统府星期三（8月2日）上午召开记者会，总统府副秘书长黄重谚说，蔡英文7月25日略感身体不适，经..."
  },
  {
    "title": "阿里、字节等多家企业捐款救助京津冀灾区",
    "link": "/realtime/china/story20230802-1419789",
    "uuid": "5a1769d1-34d2-428f-b993-04cd32390cfd",
    "summary": "中国京津冀地区连日暴雨造成严重洪涝灾情，阿里巴巴、小米、理想汽车等多家企业向灾区捐赠抗灾救灾款，支持救灾和灾后重建。据第一财经报道，阿里巴巴公益基金会星期三（8月2日）宣布，将捐赠..."
  },
  {
    "title": "中国将免征金融机构与小微企业借款合同印花税",
    "link": "/realtime/china/story20230802-1419793",
    "uuid": "da42149b-d578-4a6a-bf60-9209c4c96629",
    "summary": "中国财政部宣布，将对金融机构与小微企业签订的借款合同免征印花税，以加大对小微企业的支持，提振经济复苏。据中国财政部官网消息，中国财政部税务总局星期三（8月2日）发布《关于支持小微企..."
  },
  {
    "title": "港保安局长：外部势力回归前已处心积虑利用香港危害国安",
    "link": "/realtime/china/story20230802-1419769",
    "uuid": "f6567e2f-1ac5-42b2-849d-12effa655ca7",
    "summary": "香港保安局局长邓炳强说，外部势力早在1997年香港回归前，已经处心积虑利用香港危害中国的国家安全。据星岛日报报道，邓炳强星期三（8月2日）在社交平台上载国家安全影片系列第四集，指外..."
  },
  {
    "title": "台风“卡努”将进入东海 中国东北将出现强降雨",
    "link": "/realtime/china/story20230802-1419761",
    "uuid": "2d09fc4d-62fb-4d56-b2da-20cdff70d86b",
    "summary": "今年第6号台风“卡努”即将进入中国东海，内蒙古东部和东北部分地区将出现强暴雨。据中新社报道，中央气象台网站星期三（8月2日）发布消息，8月2日至4日，内蒙古东部、东北地区多阵雨或雷..."
  },
  {
    "title": "中共中央军委发文：推进全军不敢腐不能腐不想腐",
    "link": "/realtime/china/story20230802-1419755",
    "uuid": "f6403539-2a4c-48e0-9110-203246f1f96a",
    "summary": "中共中央军委在建军96周年之际印发全面加强军队党建的意见，要求全军一体推进不敢腐、不能腐、不想腐，为实现建军百年奋斗目标提供政治保证。据新华社星期二（8月1日）报道，中央军委日前印..."
  },
  {
    "title": "中国将扩大互联网未成年人模式管理范围",
    "link": "/realtime/china/story20230802-1419780",
    "uuid": "ad12dac8-737d-4c09-9a1b-280ef4d5ddc8",
    "summary": "为了进一步强化对未成年人使用网络的管理，中国国家互联网信息办公室将全面升级“青少年模式”为“未成年人模式”，管理范围将从APP扩大至行动智慧中端装置、应用商店，实现软硬体三方联动等..."
  },
  {
    "title": "台湾陆军中校被指向中国大陆泄露国防机密",
    "link": "/realtime/china/story20230802-1419762",
    "uuid": "bc808036-f85b-42d5-b730-faa74df1628c",
    "summary": "台湾陆军一名中校被指向中国大陆泄露国防机密，检方已获准羁押这名中校。据台湾《上报》星期三（8月2日）报道，台军陆军航空特战指挥部在战略上负责防御包括台北在内的北部地区，也被称为“龙..."
  }
]
