[
  {
    "title": "山西黄河壶口瀑布排放污水严重超标 涉事公司被罚33万人民币",
    "link": "/realtime/china/story20240302-1471667",
    "uuid": "6aa09c27-3f39-4559-9899-a749b310737b",
    "summary": "山西省临汾黄河壶口瀑布排放污水多项指标严重超标，壶口瀑布旅游开发有限公司被罚33万人民币（约6万2400新元）。根据法治日报星期六（3月2日）报道，山西省临汾市生态环境局近日对临汾..."
  },
  {
    "title": "港创科局长：有信心明年新型工业研发开支占GDP1.3%",
    "link": "/realtime/china/story20240302-1471656",
    "uuid": "8ebd8bec-d343-4e13-add1-cca05633e879",
    "summary": "香港创新科技及工业局局长孙东星期六（3月2日）说，他有信心2025年新型工业香港研发总开支占生产总值的比率，能由2022年的1.07%，上升至1.3%。综合星岛日报和香港电台报道，..."
  },
  {
    "title": "中国住建部要求摸清工薪群体需求 规划建设保障房",
    "link": "/realtime/china/story20240302-1471639",
    "uuid": "10e2b6d4-18de-4a80-8308-ae3698e8f22d",
    "summary": "中国住房城乡建设部要求各地加快建立轮候机制，摸清工薪收入群体需求，加快推动首批保障性住房项目开工建设，以高效优质推动保障性住房建设和供给。根据北京日报客户端星期六（3月2日）消息，..."
  },
  {
    "title": "据报台空军恐现退伍潮 台国防部：人力平均编现可满足战备需求",
    "link": "/realtime/china/story20240302-1471653",
    "uuid": "ff586452-6e64-4a96-8153-e27536c9c9bd",
    "summary": "针对有台湾媒体报道台空军年底恐出现飞官退伍潮，缺员将更严重，台湾国防部星期六（3月2日）说，自2020年起修调“国军飞行军官继续服现役奖助金”后，每年签约及离退人数呈常态分布、无异..."
  },
  {
    "title": "河南开封一小学疑拖欠教师工资无人上课 当地教育局称正在处理",
    "link": "/realtime/china/story20240302-1471648",
    "uuid": "8a6227fd-ebdd-421a-a874-9fe43259a8af",
    "summary": "河南开封一小学星期四（2月29日）被爆开学四天都没有老师上课。有家长透露，疑因学校欠薪半年，没有老师到岗。学校老师星期五（3月1日）回应称，所有老师已到岗，学生们已经开始正常上课。"
  },
  {
    "title": "李家超下周一赴京列席中国人大会议开幕会",
    "link": "/realtime/china/story20240302-1471675",
    "uuid": "d2d8735f-dbb6-4b74-b833-1f57d7220c79",
    "summary": "香港特首李家超将于下星期一（3月4日）赴京列席中国全国人大会议开幕会。香港政府新闻公报星期六（3月2日）公告上述消息。根据公报，香港行政长官李家超3月4日赴北京，列席3月5日举行的..."
  },
  {
    "title": "中国政协委员建议完善疫苗预防接种异常反应补偿制度",
    "link": "/realtime/china/story20240302-1471660",
    "uuid": "022b2379-d6ec-4dec-9e67-71ae4225130f",
    "summary": "中国全国政协委员朱涛提议进一步完善疫苗预防接种异常反应补偿制度，将补偿责任转移至生产者共同体。据每日经济新闻星期六（3月2日）报道，同是康希诺生物首席科学官的朱涛提交四份提案，其中..."
  },
  {
    "title": "阿里巴巴资深高管俞永福将于3月底卸任",
    "link": "/realtime/china/story20240302-1471666",
    "uuid": "2267980f-472a-4356-9f96-8eaed2f4def2",
    "summary": "阿里巴巴集团资深高管俞永福将于3月底卸任，他所承担的职务将分摊给年轻一代高管。综合彭博社和第一财经星期五（3月1日）报道，阿里巴巴集团发言人称，公司合伙人、任职时间最长的高管之一俞..."
  },
  {
    "title": "大陆客消费谨慎 澳门2月博彩收入增幅低于预期",
    "link": "/realtime/china/story20240302-1471658",
    "uuid": "5ae69e7f-3a01-41df-ba24-e67975b79f18",
    "summary": "受中国大陆游客消费趋于谨慎影响，澳门2月博彩收入增幅低于预期。据彭博社报道，澳门官方通报，农历新年八天假期，到访澳门的游客总计140万人次，为2017年以来最高水平，大陆游客占76..."
  },
  {
    "title": "中国侨联副主席：港楼市撤辣得到中央支持",
    "link": "/realtime/china/story20240302-1471654",
    "uuid": "918da4ac-63f1-4ca7-b4ae-374999610271",
    "summary": "中国侨联副主席卢文端称，香港新一份财政预算案果断提出全面撤销楼市降温措施（撤辣），是因为获得北京中央的支持。卢文端星期五（3月1日）在香港《明报》撰文称，港府内部对全面“撤辣”或部..."
  },
  {
    "title": "中使馆批印度媒体采访吴钊燮 违背一中原则",
    "link": "/realtime/china/story20240302-1471643",
    "uuid": "19191d48-f6a7-4787-acb9-049c4e0f95b7",
    "summary": "中国驻印度大使馆批评印度媒体采访台湾外交部吴钊燮，是违背一个中国原则。中国驻印度大使馆星期六（3月2日）在官方微信公众号发文说，印度某电视台星期四（2月29日）播出对台外交部长吴钊..."
  },
  {
    "title": "台海委会：将配置密录器建置船艇录影设备",
    "link": "/realtime/china/story20240302-1471637",
    "uuid": "08efd6b0-a116-4e6e-ad15-721735c45ab4",
    "summary": "金厦水域翻船案导致两岸关系恶化，台湾海委会重申，海巡人员执法于法有据，但坦言在通报和影像搜证工作方面仍有疏忽，为避免类似案件再发生，将配置密录器建置船艇录影设备。综合台湾华视新闻网..."
  },
  {
    "title": "中国神舟十七航天员乘组完成第二次出舱活动",
    "link": "/realtime/china/story20240302-1471636",
    "uuid": "b2f789f9-6cfa-497b-9c75-f069935c72d9",
    "summary": "中国神舟十七航天员乘组完成第二次出舱活动，并首次完成舱外维修任务。中国央视新闻星期六（3月2日）引述中国载人航天工程办公室消息报道，当天下午1时32分经过约八小时的出舱活动，神舟十..."
  },
  {
    "title": "中国国常会通过大规模设备更新和以旧换新行动方案",
    "link": "/realtime/china/story20240302-1471623",
    "uuid": "e45acd13-e082-40ec-ab8d-d5286d11de02",
    "summary": "中国国常会通过行动方案，要推动大规模设备更新和消费品以旧换新行动。据新华社报道，中国总理李强星期五（3月1日）主持召开国务院常务会议，审议通过《推动大规模设备更新和消费品以旧换新行..."
  },
  {
    "title": "台特勤少将陷桃色风波 被国安局列入优先汰除名单",
    "link": "/realtime/china/story20240302-1471620",
    "uuid": "bbd58f9e-925f-48e4-9e9c-915feeb1d439",
    "summary": "曾任台湾副总统赖清德万里警卫室主任的特勤中心少将谢静华，被爆出酒后在大路上与女友人亲吻后，台湾国安局对其记大过，并列入优先汰除人员的名单。综合台湾菱传媒、三立新闻网和中央社报道，互..."
  },
  {
    "title": "中使馆批罗马尼亚对中企采取歧视性排除条款",
    "link": "/realtime/china/story20240302-1471624",
    "uuid": "9acf55f7-9918-4886-afd9-85dae58e5caf",
    "summary": "中国驻罗马尼亚大使馆对罗马尼亚拒绝华为参与5G网络建设深表遗憾，并批评罗马尼亚对中企采取歧视性排除条款。据中国驻罗马尼亚官网星期六（3月2日）发布的消息，罗马尼亚政府星期四（2月2..."
  },
  {
    "title": "港财政司长：若楼市过热随时可调整应对",
    "link": "/realtime/china/story20240302-1471616",
    "uuid": "efb9df6e-9c8f-46d3-8a0f-04b127ea98cf",
    "summary": "香港新一份财政预算案宣布全面撤销楼市降温措施后，财政司长陈茂波重申，如果香港楼市再次出现过度炽热的现象，港府随时可以调整措施应对。综合香港《星岛日报》《信报》报道，陈茂波星期六（3..."
  },
  {
    "title": "台检方建请法院对涉收陆资选立委民众党前发言人判刑44个月",
    "link": "/realtime/china/story20240302-1471622",
    "uuid": "e72d2307-4ff3-49bb-92f5-0d24dfa7b893",
    "summary": "台湾桃园地检署建请法院，对涉嫌收取大陆资金参选立委的民众党桃园市党部前发言人马治薇，判处有期徒刑44个月。综合台湾《自由时报》和中时新闻网报道，马治薇曾有意代表民众党参选立委，后来..."
  },
  {
    "title": "港交所新总裁：未来发展机遇与挑战并存",
    "link": "/realtime/china/story20240302-1471619",
    "uuid": "6018656f-58f6-4d5d-b1db-66029b59140a",
    "summary": "香港交易所新任行政总裁陈翊庭星履新当天，给员工致函谈及港交所未来发展机遇与挑战并存。综合香港中通社和香港电台等报道，陈翊庭星期五（3月1日）正式上任，开启三年任期。陈翊庭在发给员工..."
  },
  {
    "title": "缅甸向中国移交今年首批在缅诈骗497名嫌犯",
    "link": "/realtime/china/story20240302-1471615",
    "uuid": "de07267d-097f-4a38-bfee-e4c038fe3699",
    "summary": "中国与缅甸执法单位今年持续加强合作，缅甸将今年首批在缅实施诈骗行为的497名嫌犯移交给中国。新华社星期五（3月1日）引述中国公安部消息报道，今年以来，中国公安部继续加强与缅甸执法部..."
  },
  {
    "title": "德意志银行据报对中国房企世茂集团提清算诉讼",
    "link": "/realtime/china/story20240302-1471612",
    "uuid": "3a78a341-e86d-4e9a-86a0-3e50d7c7cb46",
    "summary": "消息人士透露，德意志银行准备对中国房产开发商世茂集团提起清算诉讼。路透社星期五（3月1日）引述两名消息人士称，作为世茂集团债权人之一的德意志银行在发现世茂的债务重组条款不可接受后，..."
  },
  {
    "title": "台湾新竹县长疑涉贪被传讯后交保",
    "link": "/realtime/china/story20240302-1471611",
    "uuid": "943b3ecc-7bab-4675-bb21-f502f53710fe",
    "summary": "台湾新竹县的国民党籍县长杨文科疑似涉嫌贪污被传讯后交保50万新台币（约2万1289新元）。他强调自己无不法之处，将全力配合调查，希望司法公正审理还他清白。综合台湾《中国时报》和壹苹..."
  },
  {
    "title": "山东一车祸致二死六伤 司机当场被捕",
    "link": "/realtime/china/story20240302-1471607",
    "uuid": "a06739e0-d9eb-407a-b0b8-b71d7c10479b",
    "summary": "中国山东省德州市发生一起致命车祸，造成两人死亡、六人受伤，涉事司机当场被捕。据中国央视新闻报道，省德州市德城区安居苑小区南侧道路星期五（3月1日）下午1时40分左右发生一起车祸，一..."
  },
  {
    "title": "中国驻日大使：有部分外企退出中国 未出现逃离潮",
    "link": "/realtime/china/story20240302-1471606",
    "uuid": "0b0475cc-e7a9-4f76-b233-c54704e31e81",
    "summary": "中国驻日本大使吴江浩接受日本财经杂志访问时说，中国是市场经济国家，外资企业进出属于正常现象，并强调确实有部分外企退出中国，但未出现逃离潮。据中国驻日大使馆星期五（3月1日）在官网发..."
  }
]
